delimux/__init__.py
delimux/delimux.py
delimux-1.0.1.dist-info/METADATA
delimux-1.0.1.dist-info/WHEEL
delimux-1.0.1.dist-info/top_level.txt
delimux-1.0.1.dist-info/RECORD
