Metadata-Version: 2.4
Name: delimux
Version: 1.0.1
Summary: API for the delimux device
Home-page: https://gitlab.phys.ethz.ch/cmtqo-projects/delicate/delimux
Author: Sebastian Huber
Author-email: huberse@phys.ethz.ch
Requires-Python: >=3.8
Dynamic: author
Dynamic: author-email
Dynamic: description
Dynamic: description-content-type
Dynamic: home-page
Dynamic: requires-python
Dynamic: summary
